{
  "abilities": {
    "bettertrims:damage_immunity": [
      {
        "ability": {},
        "requirements": {
          "condition": "minecraft:damage_source_properties",
          "predicate": {
            "tags": [
              {
                "expected": true,
                "id": "minecraft:is_lightning"
              },
              {
                "expected": false,
                "id": "minecraft:bypasses_invulnerability"
              }
            ]
          }
        }
      }
    ]
  },
  "item_properties": {
    "bettertrims:damage_immunity": [
      {
        "item_property": {},
        "requirements": {
          "condition": "minecraft:damage_source_properties",
          "predicate": {
            "tags": [
              {
                "expected": true,
                "id": "minecraft:is_lightning"
              },
              {
                "expected": false,
                "id": "minecraft:bypasses_invulnerability"
              }
            ]
          }
        }
      }
    ]
  },
  "trim": {
    "material": "#c:copper"
  }
}